spdx_validator/__init__.py
spdx_validator/__main__.py
spdx_validator/checksum.py
spdx_validator/config.py
spdx_validator/convertor.py
spdx_validator/exception.py
spdx_validator/validator.py
spdx_validator/format/__init__.py
spdx_validator/format/factory.py
spdx_validator/format/format_flict.py
spdx_validator/format/format_interface.py
spdx_validator/format/format_json.py
spdx_validator/format/format_yaml.py
spdx_validator/var/spdx-schema-2.2.json
spdx_validator-0.1.6.dist-info/LICENSE
spdx_validator-0.1.6.dist-info/METADATA
spdx_validator-0.1.6.dist-info/WHEEL
spdx_validator-0.1.6.dist-info/entry_points.txt
spdx_validator-0.1.6.dist-info/top_level.txt
spdx_validator-0.1.6.dist-info/RECORD
