Metadata-Version: 2.1
Name: spdx-validator
Version: 0.1.6
Summary: Simple SPDX Package validator
Home-page: https://github.com/hesa/spdx_validatorr
Author: Henrik Sanklef
Author-email: hesa@sandklef.com
Classifier: Development Status :: 4 - Beta
Classifier: Environment :: Console
Classifier: Intended Audience :: Developers
Classifier: Intended Audience :: Legal Industry
Classifier: License :: OSI Approved :: GNU General Public License v3 or later (GPLv3+)
Classifier: Natural Language :: English
Classifier: Operating System :: POSIX :: Linux
Classifier: Programming Language :: Python :: 3 :: Only
Classifier: Programming Language :: Python :: 3.6
Classifier: Programming Language :: Python :: 3.7
Classifier: Programming Language :: Python :: 3.8
Classifier: Programming Language :: Python :: 3.9
Classifier: Programming Language :: Python :: 3
Classifier: Topic :: Software Development :: Quality Assurance
Requires-Python: >=3.6
License-File: LICENSE
Requires-Dist: spdx-license-list
Requires-Dist: jsonschema
Requires-Dist: PyYAML
Provides-Extra: dev
Requires-Dist: pytest (<8.0.0,>=6.2.0) ; extra == 'dev'
